kvdroid/__init__.py
kvdroid/app.py
kvdroid/base.py
kvdroid/cast.py
kvdroid/event.py
kvdroid/jclass/__init__.py
kvdroid/jclass/android/R.py
kvdroid/jclass/android/__init__.py
kvdroid/jclass/android/app/__init__.py
kvdroid/jclass/android/content/__init__.py
kvdroid/jclass/android/content/pm.py
kvdroid/jclass/android/content/res.py
kvdroid/jclass/android/graphics/__init__.py
kvdroid/jclass/android/graphics/drawable.py
kvdroid/jclass/android/hardware/__init__.py
kvdroid/jclass/android/hardware/camera2/__init__.py
kvdroid/jclass/android/hardware/camera2/params.py
kvdroid/jclass/android/location/__init__.py
kvdroid/jclass/android/media/__init__.py
kvdroid/jclass/android/net/__init__.py
kvdroid/jclass/android/net/wifi/__init__.py
kvdroid/jclass/android/os/__init__.py
kvdroid/jclass/android/os/ext.py
kvdroid/jclass/android/provider/__init__.py
kvdroid/jclass/android/speech/__init__.py
kvdroid/jclass/android/speech/tts.py
kvdroid/jclass/android/support/__init__.py
kvdroid/jclass/android/support/v4/__init__.py
kvdroid/jclass/android/support/v4/app.py
kvdroid/jclass/android/telephony/__init__.py
kvdroid/jclass/android/text/__init__.py
kvdroid/jclass/android/text/format.py
kvdroid/jclass/android/util/__init__.py
kvdroid/jclass/android/view/__init__.py
kvdroid/jclass/android/webkit/__init__.py
kvdroid/jclass/android/widget/__init__.py
kvdroid/jclass/androidx/__init__.py
kvdroid/jclass/androidx/activity/__init__.py
kvdroid/jclass/androidx/activity/result/__init__.py
kvdroid/jclass/androidx/activity/result/contract.py
kvdroid/jclass/androidx/appcompat/__init__.py
kvdroid/jclass/androidx/appcompat/app.py
kvdroid/jclass/androidx/browser/__init__.py
kvdroid/jclass/androidx/browser/customtabs.py
kvdroid/jclass/androidx/core/__init__.py
kvdroid/jclass/androidx/core/app.py
kvdroid/jclass/androidx/core/content/__init__.py
kvdroid/jclass/androidx/core/content/res.py
kvdroid/jclass/androidx/core/graphics/__init__.py
kvdroid/jclass/androidx/core/graphics/drawable.py
kvdroid-0.7.1.dist-info/LICENSE
kvdroid-0.7.1.dist-info/METADATA
kvdroid-0.7.1.dist-info/WHEEL
kvdroid-0.7.1.dist-info/RECORD
