Metadata-Version: 2.1
Name: kvdroid
Version: 0.7.1
Summary: A re-implementation of android java API in python with easy access to some Android functionalitylike Notification,Reading of Contacts, accessing Webview Cookies, etc...
License: MIT
Keywords: Android,Androidx,Python,Kivy,KivyMD,KvDroid
Author: Yunus Ceyhan
Author-email: yunus.ceyhn@gmail.com
Requires-Python: >=3.9,<4.0
Classifier: License :: OSI Approved :: MIT License
Classifier: Programming Language :: Python :: 3
Classifier: Programming Language :: Python :: 3.9
Classifier: Programming Language :: Python :: 3.10
Classifier: Programming Language :: Python :: 3.11
Classifier: Programming Language :: Python :: 3.12
Requires-Dist: pyjnius (>=1.7.0,<2.0.0)
